<?xml version="1.0" encoding="UTF-8"?>
<root>
  <row>
    <Id>1</Id>
    <FirstName>&apos;Maria&apos;</FirstName>
    <LastName>&apos;Anders&apos;</LastName>
    <City>&apos;Berlin&apos;</City>
    <Country>&apos;Germany&apos;</Country>
    <Phone>&apos;030-0074321&apos;</Phone>
  </row>
  <row>
    <Id>2</Id>
    <FirstName>&apos;Ana&apos;</FirstName>
    <LastName>&apos;Trujillo&apos;</LastName>
    <City>&apos;México D.F.&apos;</City>
    <Country>&apos;Mexico&apos;</Country>
    <Phone>&apos;(5) 555-4729&apos;</Phone>
  </row>
  <row>
    <Id>3</Id>
    <FirstName>&apos;Antonio&apos;</FirstName>
    <LastName>&apos;Moreno&apos;</LastName>
    <City>&apos;México D.F.&apos;</City>
    <Country>&apos;Mexico&apos;</Country>
    <Phone>&apos;(5) 555-3932&apos;</Phone>
  </row>
  <row>
    <Id>4</Id>
    <FirstName>&apos;Thomas&apos;</FirstName>
    <LastName>&apos;Hardy&apos;</LastName>
    <City>&apos;London&apos;</City>
    <Country>&apos;UK&apos;</Country>
    <Phone>&apos;(171) 555-7788&apos;</Phone>
  </row>
  <row>
    <Id>5</Id>
    <FirstName>&apos;Christina&apos;</FirstName>
    <LastName>&apos;Berglund&apos;</LastName>
    <City>&apos;Luleå&apos;</City>
    <Country>&apos;Sweden&apos;</Country>
    <Phone>&apos;0921-12 34 65&apos;</Phone>
  </row>
  <row>
    <Id>6</Id>
    <FirstName>&apos;Hanna&apos;</FirstName>
    <LastName>&apos;Moos&apos;</LastName>
    <City>&apos;Mannheim&apos;</City>
    <Country>&apos;Germany&apos;</Country>
    <Phone>&apos;0621-08460&apos;</Phone>
  </row>
  <row>
    <Id>7</Id>
    <FirstName>&apos;Frédérique&apos;</FirstName>
    <LastName>&apos;Citeaux&apos;</LastName>
    <City>&apos;Strasbourg&apos;</City>
    <Country>&apos;France&apos;</Country>
    <Phone>&apos;88.60.15.31&apos;</Phone>
  </row>
  <row>
    <Id>8</Id>
    <FirstName>&apos;Martín&apos;</FirstName>
    <LastName>&apos;Sommer&apos;</LastName>
    <City>&apos;Madrid&apos;</City>
    <Country>&apos;Spain&apos;</Country>
    <Phone>&apos;(91) 555 22 82&apos;</Phone>
  </row>
  <row>
    <Id>9</Id>
    <FirstName>&apos;Laurence&apos;</FirstName>
    <LastName>&apos;Lebihan&apos;</LastName>
    <City>&apos;Marseille&apos;</City>
    <Country>&apos;France&apos;</Country>
    <Phone>&apos;91.24.45.40&apos;</Phone>
  </row>
  <row>
    <Id>10</Id>
    <FirstName>&apos;Elizabeth&apos;</FirstName>
    <LastName>&apos;Lincoln&apos;</LastName>
    <City>&apos;Tsawassen&apos;</City>
    <Country>&apos;Canada&apos;</Country>
    <Phone>&apos;(604) 555-4729&apos;</Phone>
  </row>
  <row>
    <Id>11</Id>
    <FirstName>&apos;Victoria&apos;</FirstName>
    <LastName>&apos;Ashworth&apos;</LastName>
    <City>&apos;London&apos;</City>
    <Country>&apos;UK&apos;</Country>
    <Phone>&apos;(171) 555-1212&apos;</Phone>
  </row>
  <row>
    <Id>12</Id>
    <FirstName>&apos;Patricio&apos;</FirstName>
    <LastName>&apos;Simpson&apos;</LastName>
    <City>&apos;Buenos Aires&apos;</City>
    <Country>&apos;Argentina&apos;</Country>
    <Phone>&apos;(1) 135-5555&apos;</Phone>
  </row>
  <row>
    <Id>13</Id>
    <FirstName>&apos;Francisco&apos;</FirstName>
    <LastName>&apos;Chang&apos;</LastName>
    <City>&apos;México D.F.&apos;</City>
    <Country>&apos;Mexico&apos;</Country>
    <Phone>&apos;(5) 555-3392&apos;</Phone>
  </row>
  <row>
    <Id>14</Id>
    <FirstName>&apos;Yang&apos;</FirstName>
    <LastName>&apos;Wang&apos;</LastName>
    <City>&apos;Bern&apos;</City>
    <Country>&apos;Switzerland&apos;</Country>
    <Phone>&apos;0452-076545&apos;</Phone>
  </row>
  <row>
    <Id>15</Id>
    <FirstName>&apos;Pedro&apos;</FirstName>
    <LastName>&apos;Afonso&apos;</LastName>
    <City>&apos;Sao Paulo&apos;</City>
    <Country>&apos;Brazil&apos;</Country>
    <Phone>&apos;(11) 555-7647&apos;</Phone>
  </row>
  <row>
    <Id>16</Id>
    <FirstName>&apos;Elizabeth&apos;</FirstName>
    <LastName>&apos;Brown&apos;</LastName>
    <City>&apos;London&apos;</City>
    <Country>&apos;UK&apos;</Country>
    <Phone>&apos;(171) 555-2282&apos;</Phone>
  </row>
  <row>
    <Id>17</Id>
    <FirstName>&apos;Sven&apos;</FirstName>
    <LastName>&apos;Ottlieb&apos;</LastName>
    <City>&apos;Aachen&apos;</City>
    <Country>&apos;Germany&apos;</Country>
    <Phone>&apos;0241-039123&apos;</Phone>
  </row>
  <row>
    <Id>18</Id>
    <FirstName>&apos;Janine&apos;</FirstName>
    <LastName>&apos;Labrune&apos;</LastName>
    <City>&apos;Nantes&apos;</City>
    <Country>&apos;France&apos;</Country>
    <Phone>&apos;40.67.88.88&apos;</Phone>
  </row>
  <row>
    <Id>19</Id>
    <FirstName>&apos;Ann&apos;</FirstName>
    <LastName>&apos;Devon&apos;</LastName>
    <City>&apos;London&apos;</City>
    <Country>&apos;UK&apos;</Country>
    <Phone>&apos;(171) 555-0297&apos;</Phone>
  </row>
  <row>
    <Id>20</Id>
    <FirstName>&apos;Roland&apos;</FirstName>
    <LastName>&apos;Mendel&apos;</LastName>
    <City>&apos;Graz&apos;</City>
    <Country>&apos;Austria&apos;</Country>
    <Phone>&apos;7675-3425&apos;</Phone>
  </row>
  <row>
    <Id>21</Id>
    <FirstName>&apos;Aria&apos;</FirstName>
    <LastName>&apos;Cruz&apos;</LastName>
    <City>&apos;Sao Paulo&apos;</City>
    <Country>&apos;Brazil&apos;</Country>
    <Phone>&apos;(11) 555-9857&apos;</Phone>
  </row>
  <row>
    <Id>22</Id>
    <FirstName>&apos;Diego&apos;</FirstName>
    <LastName>&apos;Roel&apos;</LastName>
    <City>&apos;Madrid&apos;</City>
    <Country>&apos;Spain&apos;</Country>
    <Phone>&apos;(91) 555 94 44&apos;</Phone>
  </row>
  <row>
    <Id>23</Id>
    <FirstName>&apos;Martine&apos;</FirstName>
    <LastName>&apos;Rancé&apos;</LastName>
    <City>&apos;Lille&apos;</City>
    <Country>&apos;France&apos;</Country>
    <Phone>&apos;20.16.10.16&apos;</Phone>
  </row>
  <row>
    <Id>24</Id>
    <FirstName>&apos;Maria&apos;</FirstName>
    <LastName>&apos;Larsson&apos;</LastName>
    <City>&apos;Bräcke&apos;</City>
    <Country>&apos;Sweden&apos;</Country>
    <Phone>&apos;0695-34 67 21&apos;</Phone>
  </row>
  <row>
    <Id>25</Id>
    <FirstName>&apos;Peter&apos;</FirstName>
    <LastName>&apos;Franken&apos;</LastName>
    <City>&apos;München&apos;</City>
    <Country>&apos;Germany&apos;</Country>
    <Phone>&apos;089-0877310&apos;</Phone>
  </row>
  <row>
    <Id>26</Id>
    <FirstName>&apos;Carine&apos;</FirstName>
    <LastName>&apos;Schmitt&apos;</LastName>
    <City>&apos;Nantes&apos;</City>
    <Country>&apos;France&apos;</Country>
    <Phone>&apos;40.32.21.21&apos;</Phone>
  </row>
  <row>
    <Id>27</Id>
    <FirstName>&apos;Paolo&apos;</FirstName>
    <LastName>&apos;Accorti&apos;</LastName>
    <City>&apos;Torino&apos;</City>
    <Country>&apos;Italy&apos;</Country>
    <Phone>&apos;011-4988260&apos;</Phone>
  </row>
  <row>
    <Id>28</Id>
    <FirstName>&apos;Lino&apos;</FirstName>
    <LastName>&apos;Rodriguez&apos;</LastName>
    <City>&apos;Lisboa&apos;</City>
    <Country>&apos;Portugal&apos;</Country>
    <Phone>&apos;(1) 354-2534&apos;</Phone>
  </row>
  <row>
    <Id>29</Id>
    <FirstName>&apos;Eduardo&apos;</FirstName>
    <LastName>&apos;Saavedra&apos;</LastName>
    <City>&apos;Barcelona&apos;</City>
    <Country>&apos;Spain&apos;</Country>
    <Phone>&apos;(93) 203 4560&apos;</Phone>
  </row>
  <row>
    <Id>30</Id>
    <FirstName>&apos;José&apos;</FirstName>
    <LastName>&apos;Pedro Freyre&apos;</LastName>
    <City>&apos;Sevilla&apos;</City>
    <Country>&apos;Spain&apos;</Country>
    <Phone>&apos;(95) 555 82 82&apos;</Phone>
  </row>
  <row>
    <Id>31</Id>
    <FirstName>&apos;André&apos;</FirstName>
    <LastName>&apos;Fonseca&apos;</LastName>
    <City>&apos;Campinas&apos;</City>
    <Country>&apos;Brazil&apos;</Country>
    <Phone>&apos;(11) 555-9482&apos;</Phone>
  </row>
  <row>
    <Id>32</Id>
    <FirstName>&apos;Howard&apos;</FirstName>
    <LastName>&apos;Snyder&apos;</LastName>
    <City>&apos;Eugene&apos;</City>
    <Country>&apos;USA&apos;</Country>
    <Phone>&apos;(503) 555-7555&apos;</Phone>
  </row>
  <row>
    <Id>33</Id>
    <FirstName>&apos;Manuel&apos;</FirstName>
    <LastName>&apos;Pereira&apos;</LastName>
    <City>&apos;Caracas&apos;</City>
    <Country>&apos;Venezuela&apos;</Country>
    <Phone>&apos;(2) 283-2951&apos;</Phone>
  </row>
  <row>
    <Id>34</Id>
    <FirstName>&apos;Mario&apos;</FirstName>
    <LastName>&apos;Pontes&apos;</LastName>
    <City>&apos;Rio de Janeiro&apos;</City>
    <Country>&apos;Brazil&apos;</Country>
    <Phone>&apos;(21) 555-0091&apos;</Phone>
  </row>
  <row>
    <Id>35</Id>
    <FirstName>&apos;Carlos&apos;</FirstName>
    <LastName>&apos;Hernández&apos;</LastName>
    <City>&apos;San Cristóbal&apos;</City>
    <Country>&apos;Venezuela&apos;</Country>
    <Phone>&apos;(5) 555-1340&apos;</Phone>
  </row>
  <row>
    <Id>36</Id>
    <FirstName>&apos;Yoshi&apos;</FirstName>
    <LastName>&apos;Latimer&apos;</LastName>
    <City>&apos;Elgin&apos;</City>
    <Country>&apos;USA&apos;</Country>
    <Phone>&apos;(503) 555-6874&apos;</Phone>
  </row>
  <row>
    <Id>37</Id>
    <FirstName>&apos;Patricia&apos;</FirstName>
    <LastName>&apos;McKenna&apos;</LastName>
    <City>&apos;Cork&apos;</City>
    <Country>&apos;Ireland&apos;</Country>
    <Phone>&apos;2967 542&apos;</Phone>
  </row>
  <row>
    <Id>38</Id>
    <FirstName>&apos;Helen&apos;</FirstName>
    <LastName>&apos;Bennett&apos;</LastName>
    <City>&apos;Cowes&apos;</City>
    <Country>&apos;UK&apos;</Country>
    <Phone>&apos;(198) 555-8888&apos;</Phone>
  </row>
  <row>
    <Id>39</Id>
    <FirstName>&apos;Philip&apos;</FirstName>
    <LastName>&apos;Cramer&apos;</LastName>
    <City>&apos;Brandenburg&apos;</City>
    <Country>&apos;Germany&apos;</Country>
    <Phone>&apos;0555-09876&apos;</Phone>
  </row>
  <row>
    <Id>40</Id>
    <FirstName>&apos;Daniel&apos;</FirstName>
    <LastName>&apos;Tonini&apos;</LastName>
    <City>&apos;Versailles&apos;</City>
    <Country>&apos;France&apos;</Country>
    <Phone>&apos;30.59.84.10&apos;</Phone>
  </row>
  <row>
    <Id>41</Id>
    <FirstName>&apos;Annette&apos;</FirstName>
    <LastName>&apos;Roulet&apos;</LastName>
    <City>&apos;Toulouse&apos;</City>
    <Country>&apos;France&apos;</Country>
    <Phone>&apos;61.77.61.10&apos;</Phone>
  </row>
  <row>
    <Id>42</Id>
    <FirstName>&apos;Yoshi&apos;</FirstName>
    <LastName>&apos;Tannamuri&apos;</LastName>
    <City>&apos;Vancouver&apos;</City>
    <Country>&apos;Canada&apos;</Country>
    <Phone>&apos;(604) 555-3392&apos;</Phone>
  </row>
  <row>
    <Id>43</Id>
    <FirstName>&apos;John&apos;</FirstName>
    <LastName>&apos;Steel&apos;</LastName>
    <City>&apos;Walla Walla&apos;</City>
    <Country>&apos;USA&apos;</Country>
    <Phone>&apos;(509) 555-7969&apos;</Phone>
  </row>
  <row>
    <Id>44</Id>
    <FirstName>&apos;Renate&apos;</FirstName>
    <LastName>&apos;Messner&apos;</LastName>
    <City>&apos;Frankfurt a.M.&apos;</City>
    <Country>&apos;Germany&apos;</Country>
    <Phone>&apos;069-0245984&apos;</Phone>
  </row>
  <row>
    <Id>45</Id>
    <FirstName>&apos;Jaime&apos;</FirstName>
    <LastName>&apos;Yorres&apos;</LastName>
    <City>&apos;San Francisco&apos;</City>
    <Country>&apos;USA&apos;</Country>
    <Phone>&apos;(415) 555-5938&apos;</Phone>
  </row>
  <row>
    <Id>46</Id>
    <FirstName>&apos;Carlos&apos;</FirstName>
    <LastName>&apos;González&apos;</LastName>
    <City>&apos;Barquisimeto&apos;</City>
    <Country>&apos;Venezuela&apos;</Country>
    <Phone>&apos;(9) 331-6954&apos;</Phone>
  </row>
  <row>
    <Id>47</Id>
    <FirstName>&apos;Felipe&apos;</FirstName>
    <LastName>&apos;Izquierdo&apos;</LastName>
    <City>&apos;I. de Margarita&apos;</City>
    <Country>&apos;Venezuela&apos;</Country>
    <Phone>&apos;(8) 34-56-12&apos;</Phone>
  </row>
  <row>
    <Id>48</Id>
    <FirstName>&apos;Fran&apos;</FirstName>
    <LastName>&apos;Wilson&apos;</LastName>
    <City>&apos;Portland&apos;</City>
    <Country>&apos;USA&apos;</Country>
    <Phone>&apos;(503) 555-9573&apos;</Phone>
  </row>
  <row>
    <Id>49</Id>
    <FirstName>&apos;Giovanni&apos;</FirstName>
    <LastName>&apos;Rovelli&apos;</LastName>
    <City>&apos;Bergamo&apos;</City>
    <Country>&apos;Italy&apos;</Country>
    <Phone>&apos;035-640230&apos;</Phone>
  </row>
  <row>
    <Id>50</Id>
    <FirstName>&apos;Catherine&apos;</FirstName>
    <LastName>&apos;Dewey&apos;</LastName>
    <City>&apos;Bruxelles&apos;</City>
    <Country>&apos;Belgium&apos;</Country>
    <Phone>&apos;(02) 201 24 67&apos;</Phone>
  </row>
  <row>
    <Id>51</Id>
    <FirstName>&apos;Jean&apos;</FirstName>
    <LastName>&apos;Fresnière&apos;</LastName>
    <City>&apos;Montréal&apos;</City>
    <Country>&apos;Canada&apos;</Country>
    <Phone>&apos;(514) 555-8054&apos;</Phone>
  </row>
  <row>
    <Id>52</Id>
    <FirstName>&apos;Alexander&apos;</FirstName>
    <LastName>&apos;Feuer&apos;</LastName>
    <City>&apos;Leipzig&apos;</City>
    <Country>&apos;Germany&apos;</Country>
    <Phone>&apos;0342-023176&apos;</Phone>
  </row>
  <row>
    <Id>53</Id>
    <FirstName>&apos;Simon&apos;</FirstName>
    <LastName>&apos;Crowther&apos;</LastName>
    <City>&apos;London&apos;</City>
    <Country>&apos;UK&apos;</Country>
    <Phone>&apos;(171) 555-7733&apos;</Phone>
  </row>
  <row>
    <Id>54</Id>
    <FirstName>&apos;Yvonne&apos;</FirstName>
    <LastName>&apos;Moncada&apos;</LastName>
    <City>&apos;Buenos Aires&apos;</City>
    <Country>&apos;Argentina&apos;</Country>
    <Phone>&apos;(1) 135-5333&apos;</Phone>
  </row>
  <row>
    <Id>55</Id>
    <FirstName>&apos;Rene&apos;</FirstName>
    <LastName>&apos;Phillips&apos;</LastName>
    <City>&apos;Anchorage&apos;</City>
    <Country>&apos;USA&apos;</Country>
    <Phone>&apos;(907) 555-7584&apos;</Phone>
  </row>
  <row>
    <Id>56</Id>
    <FirstName>&apos;Henriette&apos;</FirstName>
    <LastName>&apos;Pfalzheim&apos;</LastName>
    <City>&apos;Köln&apos;</City>
    <Country>&apos;Germany&apos;</Country>
    <Phone>&apos;0221-0644327&apos;</Phone>
  </row>
  <row>
    <Id>57</Id>
    <FirstName>&apos;Marie&apos;</FirstName>
    <LastName>&apos;Bertrand&apos;</LastName>
    <City>&apos;Paris&apos;</City>
    <Country>&apos;France&apos;</Country>
    <Phone>&apos;(1) 42.34.22.66&apos;</Phone>
  </row>
  <row>
    <Id>58</Id>
    <FirstName>&apos;Guillermo&apos;</FirstName>
    <LastName>&apos;Fernández&apos;</LastName>
    <City>&apos;México D.F.&apos;</City>
    <Country>&apos;Mexico&apos;</Country>
    <Phone>&apos;(5) 552-3745&apos;</Phone>
  </row>
  <row>
    <Id>59</Id>
    <FirstName>&apos;Georg&apos;</FirstName>
    <LastName>&apos;Pipps&apos;</LastName>
    <City>&apos;Salzburg&apos;</City>
    <Country>&apos;Austria&apos;</Country>
    <Phone>&apos;6562-9722&apos;</Phone>
  </row>
  <row>
    <Id>60</Id>
    <FirstName>&apos;Isabel&apos;</FirstName>
    <LastName>&apos;de Castro&apos;</LastName>
    <City>&apos;Lisboa&apos;</City>
    <Country>&apos;Portugal&apos;</Country>
    <Phone>&apos;(1) 356-5634&apos;</Phone>
  </row>
  <row>
    <Id>61</Id>
    <FirstName>&apos;Bernardo&apos;</FirstName>
    <LastName>&apos;Batista&apos;</LastName>
    <City>&apos;Rio de Janeiro&apos;</City>
    <Country>&apos;Brazil&apos;</Country>
    <Phone>&apos;(21) 555-4252&apos;</Phone>
  </row>
  <row>
    <Id>62</Id>
    <FirstName>&apos;Lúcia&apos;</FirstName>
    <LastName>&apos;Carvalho&apos;</LastName>
    <City>&apos;Sao Paulo&apos;</City>
    <Country>&apos;Brazil&apos;</Country>
    <Phone>&apos;(11) 555-1189&apos;</Phone>
  </row>
  <row>
    <Id>63</Id>
    <FirstName>&apos;Horst&apos;</FirstName>
    <LastName>&apos;Kloss&apos;</LastName>
    <City>&apos;Cunewalde&apos;</City>
    <Country>&apos;Germany&apos;</Country>
    <Phone>&apos;0372-035188&apos;</Phone>
  </row>
  <row>
    <Id>64</Id>
    <FirstName>&apos;Sergio&apos;</FirstName>
    <LastName>&apos;Gutiérrez&apos;</LastName>
    <City>&apos;Buenos Aires&apos;</City>
    <Country>&apos;Argentina&apos;</Country>
    <Phone>&apos;(1) 123-5555&apos;</Phone>
  </row>
  <row>
    <Id>65</Id>
    <FirstName>&apos;Paula&apos;</FirstName>
    <LastName>&apos;Wilson&apos;</LastName>
    <City>&apos;Albuquerque&apos;</City>
    <Country>&apos;USA&apos;</Country>
    <Phone>&apos;(505) 555-5939&apos;</Phone>
  </row>
  <row>
    <Id>66</Id>
    <FirstName>&apos;Maurizio&apos;</FirstName>
    <LastName>&apos;Moroni&apos;</LastName>
    <City>&apos;Reggio Emilia&apos;</City>
    <Country>&apos;Italy&apos;</Country>
    <Phone>&apos;0522-556721&apos;</Phone>
  </row>
  <row>
    <Id>67</Id>
    <FirstName>&apos;Janete&apos;</FirstName>
    <LastName>&apos;Limeira&apos;</LastName>
    <City>&apos;Rio de Janeiro&apos;</City>
    <Country>&apos;Brazil&apos;</Country>
    <Phone>&apos;(21) 555-3412&apos;</Phone>
  </row>
  <row>
    <Id>68</Id>
    <FirstName>&apos;Michael&apos;</FirstName>
    <LastName>&apos;Holz&apos;</LastName>
    <City>&apos;Genève&apos;</City>
    <Country>&apos;Switzerland&apos;</Country>
    <Phone>&apos;0897-034214&apos;</Phone>
  </row>
  <row>
    <Id>69</Id>
    <FirstName>&apos;Alejandra&apos;</FirstName>
    <LastName>&apos;Camino&apos;</LastName>
    <City>&apos;Madrid&apos;</City>
    <Country>&apos;Spain&apos;</Country>
    <Phone>&apos;(91) 745 6200&apos;</Phone>
  </row>
  <row>
    <Id>70</Id>
    <FirstName>&apos;Jonas&apos;</FirstName>
    <LastName>&apos;Bergulfsen&apos;</LastName>
    <City>&apos;Stavern&apos;</City>
    <Country>&apos;Norway&apos;</Country>
    <Phone>&apos;07-98 92 35&apos;</Phone>
  </row>
  <row>
    <Id>71</Id>
    <FirstName>&apos;Jose&apos;</FirstName>
    <LastName>&apos;Pavarotti&apos;</LastName>
    <City>&apos;Boise&apos;</City>
    <Country>&apos;USA&apos;</Country>
    <Phone>&apos;(208) 555-8097&apos;</Phone>
  </row>
  <row>
    <Id>72</Id>
    <FirstName>&apos;Hari&apos;</FirstName>
    <LastName>&apos;Kumar&apos;</LastName>
    <City>&apos;London&apos;</City>
    <Country>&apos;UK&apos;</Country>
    <Phone>&apos;(171) 555-1717&apos;</Phone>
  </row>
  <row>
    <Id>73</Id>
    <FirstName>&apos;Jytte&apos;</FirstName>
    <LastName>&apos;Petersen&apos;</LastName>
    <City>&apos;Kobenhavn&apos;</City>
    <Country>&apos;Denmark&apos;</Country>
    <Phone>&apos;31 12 34 56&apos;</Phone>
  </row>
  <row>
    <Id>74</Id>
    <FirstName>&apos;Dominique&apos;</FirstName>
    <LastName>&apos;Perrier&apos;</LastName>
    <City>&apos;Paris&apos;</City>
    <Country>&apos;France&apos;</Country>
    <Phone>&apos;(1) 47.55.60.10&apos;</Phone>
  </row>
  <row>
    <Id>75</Id>
    <FirstName>&apos;Art&apos;</FirstName>
    <LastName>&apos;Braunschweiger&apos;</LastName>
    <City>&apos;Lander&apos;</City>
    <Country>&apos;USA&apos;</Country>
    <Phone>&apos;(307) 555-4680&apos;</Phone>
  </row>
  <row>
    <Id>76</Id>
    <FirstName>&apos;Pascale&apos;</FirstName>
    <LastName>&apos;Cartrain&apos;</LastName>
    <City>&apos;Charleroi&apos;</City>
    <Country>&apos;Belgium&apos;</Country>
    <Phone>&apos;(071) 23 67 22 20&apos;</Phone>
  </row>
  <row>
    <Id>77</Id>
    <FirstName>&apos;Liz&apos;</FirstName>
    <LastName>&apos;Nixon&apos;</LastName>
    <City>&apos;Portland&apos;</City>
    <Country>&apos;USA&apos;</Country>
    <Phone>&apos;(503) 555-3612&apos;</Phone>
  </row>
  <row>
    <Id>78</Id>
    <FirstName>&apos;Liu&apos;</FirstName>
    <LastName>&apos;Wong&apos;</LastName>
    <City>&apos;Butte&apos;</City>
    <Country>&apos;USA&apos;</Country>
    <Phone>&apos;(406) 555-5834&apos;</Phone>
  </row>
  <row>
    <Id>79</Id>
    <FirstName>&apos;Karin&apos;</FirstName>
    <LastName>&apos;Josephs&apos;</LastName>
    <City>&apos;Münster&apos;</City>
    <Country>&apos;Germany&apos;</Country>
    <Phone>&apos;0251-031259&apos;</Phone>
  </row>
  <row>
    <Id>80</Id>
    <FirstName>&apos;Miguel&apos;</FirstName>
    <LastName>&apos;Angel Paolino&apos;</LastName>
    <City>&apos;México D.F.&apos;</City>
    <Country>&apos;Mexico&apos;</Country>
    <Phone>&apos;(5) 555-2933&apos;</Phone>
  </row>
  <row>
    <Id>81</Id>
    <FirstName>&apos;Anabela&apos;</FirstName>
    <LastName>&apos;Domingues&apos;</LastName>
    <City>&apos;Sao Paulo&apos;</City>
    <Country>&apos;Brazil&apos;</Country>
    <Phone>&apos;(11) 555-2167&apos;</Phone>
  </row>
  <row>
    <Id>82</Id>
    <FirstName>&apos;Helvetius&apos;</FirstName>
    <LastName>&apos;Nagy&apos;</LastName>
    <City>&apos;Kirkland&apos;</City>
    <Country>&apos;USA&apos;</Country>
    <Phone>&apos;(206) 555-8257&apos;</Phone>
  </row>
  <row>
    <Id>83</Id>
    <FirstName>&apos;Palle&apos;</FirstName>
    <LastName>&apos;Ibsen&apos;</LastName>
    <City>&apos;Århus&apos;</City>
    <Country>&apos;Denmark&apos;</Country>
    <Phone>&apos;86 21 32 43&apos;</Phone>
  </row>
  <row>
    <Id>84</Id>
    <FirstName>&apos;Mary&apos;</FirstName>
    <LastName>&apos;Saveley&apos;</LastName>
    <City>&apos;Lyon&apos;</City>
    <Country>&apos;France&apos;</Country>
    <Phone>&apos;78.32.54.86&apos;</Phone>
  </row>
  <row>
    <Id>85</Id>
    <FirstName>&apos;Paul&apos;</FirstName>
    <LastName>&apos;Henriot&apos;</LastName>
    <City>&apos;Reims&apos;</City>
    <Country>&apos;France&apos;</Country>
    <Phone>&apos;26.47.15.10&apos;</Phone>
  </row>
  <row>
    <Id>86</Id>
    <FirstName>&apos;Rita&apos;</FirstName>
    <LastName>&apos;Müller&apos;</LastName>
    <City>&apos;Stuttgart&apos;</City>
    <Country>&apos;Germany&apos;</Country>
    <Phone>&apos;0711-020361&apos;</Phone>
  </row>
  <row>
    <Id>87</Id>
    <FirstName>&apos;Pirkko&apos;</FirstName>
    <LastName>&apos;Koskitalo&apos;</LastName>
    <City>&apos;Oulu&apos;</City>
    <Country>&apos;Finland&apos;</Country>
    <Phone>&apos;981-443655&apos;</Phone>
  </row>
  <row>
    <Id>88</Id>
    <FirstName>&apos;Paula&apos;</FirstName>
    <LastName>&apos;Parente&apos;</LastName>
    <City>&apos;Resende&apos;</City>
    <Country>&apos;Brazil&apos;</Country>
    <Phone>&apos;(14) 555-8122&apos;</Phone>
  </row>
  <row>
    <Id>89</Id>
    <FirstName>&apos;Karl&apos;</FirstName>
    <LastName>&apos;Jablonski&apos;</LastName>
    <City>&apos;Seattle&apos;</City>
    <Country>&apos;USA&apos;</Country>
    <Phone>&apos;(206) 555-4112&apos;</Phone>
  </row>
  <row>
    <Id>90</Id>
    <FirstName>&apos;Matti&apos;</FirstName>
    <LastName>&apos;Karttunen&apos;</LastName>
    <City>&apos;Helsinki&apos;</City>
    <Country>&apos;Finland&apos;</Country>
    <Phone>&apos;90-224 8858&apos;</Phone>
  </row>
  <row>
    <Id>91</Id>
    <FirstName>&apos;Zbyszek&apos;</FirstName>
    <LastName>&apos;Piestrzeniewicz&apos;</LastName>
    <City>&apos;Warszawa&apos;</City>
    <Country>&apos;Poland&apos;</Country>
    <Phone>&apos;(26) 642-7012&apos;</Phone>
  </row>
</root>